tess_asteroids/__init__.py
tess_asteroids/data/straps.csv
tess_asteroids/movingtpf.py
tess_asteroids/utils.py
tess_asteroids-1.4.3.dist-info/METADATA
tess_asteroids-1.4.3.dist-info/WHEEL
tess_asteroids-1.4.3.dist-info/licenses/LICENSE
tess_asteroids-1.4.3.dist-info/RECORD
