Metadata-Version: 2.4
Name: tess-asteroids
Version: 1.4.3
Summary: Create TPFs and LCs for solar system asteroids observed by NASA's TESS mission.
License: MIT
License-File: LICENSE
Author: Amy Tuson
Author-email: amy.l.tuson@nasa.gov
Requires-Python: >=3.9,<3.13
Classifier: License :: OSI Approved :: MIT License
Classifier: Programming Language :: Python :: 3
Classifier: Programming Language :: Python :: 3.9
Classifier: Programming Language :: Python :: 3.10
Classifier: Programming Language :: Python :: 3.11
Classifier: Programming Language :: Python :: 3.12
Requires-Dist: astropy (>=5.3.4,<6.0.0)
Requires-Dist: fbpca (>=1.0,<2.0)
Requires-Dist: lkprf (>=1.1.1,<2.0.0)
Requires-Dist: lkspacecraft (>=1.0.5,<2.0.0)
Requires-Dist: matplotlib (>=3.9,<4.0)
Requires-Dist: numpy (>=1.26.4,<2.0.0)
Requires-Dist: pandas (>=2.0,<3.0)
Requires-Dist: patsy (>=0.5.6,<0.6.0)
Requires-Dist: tess-ephem (>=0.6.3,<0.7.0)
Requires-Dist: tesscube (>=1.2,<2.0)
Requires-Dist: tesswcs (>=1.7.0,<2.0.0)
Requires-Dist: tqdm (>=4.67.1,<5.0.0)
